dcase_models/__init__.py
dcase_models/version.py
dcase_models/data/__init__.py
dcase_models/data/data_augmentation.py
dcase_models/data/data_generator.py
dcase_models/data/dataset_base.py
dcase_models/data/datasets.py
dcase_models/data/feature_extractor.py
dcase_models/data/features.py
dcase_models/data/scaler.py
dcase_models/model/__init__.py
dcase_models/model/container.py
dcase_models/model/models.py
dcase_models/util/__init__.py
dcase_models/util/callbacks.py
dcase_models/util/data.py
dcase_models/util/events.py
dcase_models/util/files.py
dcase_models/util/gui.py
dcase_models/util/metrics.py
dcase_models/util/misc.py
dcase_models/util/ui.py
tests/__init__.py
tests/conftest.py
tests/test_container.py
tests/test_data_augmentation.py
tests/test_data_generator.py
tests/test_dataset.py
tests/test_feature_extractor.py
tests/test_features.py
tests/test_models.py
tests/test_scaler.py
tests/test_util.py
visualization/__init__.py
visualization/app.py
visualization/callbacks.py
visualization/figures.py
visualization/index.py
visualization/layout.py
DCASE_models-0.2.0rc2.dist-info/LICENSE
DCASE_models-0.2.0rc2.dist-info/METADATA
DCASE_models-0.2.0rc2.dist-info/WHEEL
DCASE_models-0.2.0rc2.dist-info/top_level.txt
DCASE_models-0.2.0rc2.dist-info/RECORD
