Metadata-Version: 2.1
Name: DCASE-models
Version: 0.2.0rc2
Summary: Python library for rapid prototyping of environmental sound analysis systems
Home-page: https://github.com/pzinemanas/DCASE-models
Author: Pablo Zinemanas
Author-email: pablo.zinemanas@upf.edu
License: UNKNOWN
Download-URL: http://github.com/pzinemanas/DCASE-models/releases
Platform: UNKNOWN
Classifier: Programming Language :: Python :: 3
Classifier: License :: OSI Approved :: MIT License
Classifier: Operating System :: OS Independent
Requires-Python: >=3.6
License-File: LICENSE
Requires-Dist: numpy (>=1.1)
Requires-Dist: pandas (>=0.25)
Requires-Dist: SoundFile (>=0.1)
Requires-Dist: PyYAML (>=5.0)
Requires-Dist: librosa (>=0.7)
Requires-Dist: scikit-learn (>=0.20)
Requires-Dist: wget (>=3.0)
Requires-Dist: sox (<1.4)
Requires-Dist: sed-eval (>=0.2)
Provides-Extra: autopool
Requires-Dist: autopool (==0.1.0) ; extra == 'autopool'
Provides-Extra: docs
Requires-Dist: numpydoc ; extra == 'docs'
Requires-Dist: sphinx (!=1.3.1) ; extra == 'docs'
Requires-Dist: sphinx-rtd-theme ; extra == 'docs'
Provides-Extra: keras_tf
Requires-Dist: tensorflow (<1.14) ; extra == 'keras_tf'
Requires-Dist: keras (==2.2.4) ; extra == 'keras_tf'
Provides-Extra: keras_tf_gpu
Requires-Dist: tensorflow-gpu (<1.14) ; extra == 'keras_tf_gpu'
Requires-Dist: keras (==2.2.4) ; extra == 'keras_tf_gpu'
Provides-Extra: openl3
Requires-Dist: openl3 (==0.3.1) ; extra == 'openl3'
Provides-Extra: tests
Requires-Dist: pytest (>=5.4.3) ; extra == 'tests'
Requires-Dist: pytest-cov (>=2.11.1) ; extra == 'tests'
Provides-Extra: tf2
Requires-Dist: tensorflow (>2.0) ; extra == 'tf2'
Provides-Extra: visualization
Requires-Dist: plotly (==4.5.0) ; extra == 'visualization'
Requires-Dist: dash (==1.8.0) ; extra == 'visualization'
Requires-Dist: dash-bootstrap-components (==0.8.1) ; extra == 'visualization'
Requires-Dist: dash-audio-components (==1.2.0) ; extra == 'visualization'
